mrProject/mr projekt/2_Instruction_Decode/registerbank.vhd
-- mehrerer prozesse
-- def mult integer values, set entsprechend clk [write log, bit muss true sein für access]
-- intra prozess: zwei prozesse für multiplexer, demultiplexer
-- intra prozess: write [vorerste auslassen, keep in mind tho]

library ieee;
use ieee.std_logic_1164.all;
use ieee.numeric_std.all;

entity registerbank is 
    port(clk : in std_logic;
        dIn : in signed(31 downto 0); --input
        dOutA : out signed(31 downto 0); --outputA
        dOutB : out signed(31 downto 0); --outputB
        selA : in signed(4 downto 0); --Registernr für dOutA
        selB : in signed(4 downto 0); --Registernr für dOutB
        selD : in signed(4 downto 0); --Registernr für dIn
        wE : in std_logic);
end entity registerbank; 

architecture behaviour of registerbank is 
    type regArray is array(0 to 31) of signed(31 downto 0);
    signal registers : regArray;
begin
      reg_mult : process (selA, selB, registers) is
        begin 
            dOutA <= registers(to_integer(unsigned(selA)));
            dOutB <= registers(to_integer(unsigned(selB)));
    end process reg_mult;

      reg_demult : process (clk, dIn, selD, wE, registers) is
        begin 
            if rising_edge(clk) AND (wE = '1') then registers(to_integer(unsigned(selD))) <= dIn;
        end if;
    end process reg_demult;
    end architecture behaviour;


    --select register über name christopher ist switch hater

mrProject/mr projekt/2_Instruction_Decode/registerbankTest.vhd
library ieee;
use ieee.std_logic_1164.all;
use ieee.numeric_std.all;

entity registerbankTest is 
    generic(	periodC	: time		:= 10 ns;
            cyclesC	: integer	:= 100);
end entity registerbankTest; 


architecture testbench of registerbankTest is

    component registerbank is
        port(clk : in std_logic;
            dIn : in signed(31 downto 0); --input
            dOutA : out signed(31 downto 0); --outputA
            dOutB : out signed(31 downto 0); --outputB
            selA : in STD_LOGIC_VECTOR(4 downto 0); --Registernr für dOutA
            selB : in STD_LOGIC_VECTOR(4 downto 0); --Registernr für dOutB
            selD : in STD_LOGIC_VECTOR(4 downto 0); --Registernr für dIn
            wE : in std_logic);
    end component registerbank; 
    
    signal clk, wE : std_logic;
    signal dIn, dOutA, dOutB : signed(31 downto 0);
    signal selA, selB, selD : STD_LOGIC_VECTOR(4 downto 0);
begin
    registerbankI: registerbank	port map (clk, dIn, dOutA, dOutB, selA, selB, selD, wE);

    registerbankP: process is
        begin
            wE <= '1';
            selA <= STD_LOGIC_VECTOR(to_signed(0, 5));
            selB <= STD_LOGIC_VECTOR(to_signed(10, 5));
            for i in 0 to 31 loop
                selD <= STD_LOGIC_VECTOR(to_signed(i, 5));
                dIn <= to_signed(i, 32);
                clk <= '0';
                wait for periodC;
                clk <= '1'; 
                wait for periodC;
            end loop; 
            
            clk <= '0';
            dIn <= "10101010101010101010101010101010";
            selD <= STD_LOGIC_VECTOR(to_signed(0, 5));
            wE <= '1';
	        wait for periodC;
            clk <= '1';
	        wait for periodC;
            clk <= '0';
            dIn <= "01010101010101010101010101010101";
            selD <= STD_LOGIC_VECTOR(to_signed(10, 5));
            wE <= '1';
	        wait for periodC;
            clk <= '1';
	        wait for periodC;
            wait;
        end process registerbankP;
    end architecture testbench;

mrProject/mr projekt/registerbankTest.vcd
$date
  Wed Jan 29 10:35:48 2025
$end
$version
  GHDL v0
$end
$timescale
  1 fs
$end
$scope module standard $end
$upscope $end
$scope module std_logic_1164 $end
$upscope $end
$scope module numeric_std $end
$upscope $end
$scope module registerbanktest $end
$var reg 1 ! clk $end
$var reg 1 " we $end
$var reg 32 # din[31:0] $end
$var reg 32 $ douta[31:0] $end
$var reg 32 % doutb[31:0] $end
$var reg 5 & sela[4:0] $end
$var reg 5 ' selb[4:0] $end
$var reg 5 ( seld[4:0] $end
$scope module registerbanki $end
$var reg 1 ) clk $end
$var reg 32 * din[31:0] $end
$var reg 32 + douta[31:0] $end
$var reg 32 , doutb[31:0] $end
$var reg 5 - sela[4:0] $end
$var reg 5 . selb[4:0] $end
$var reg 5 / seld[4:0] $end
$var reg 1 0 we $end
$comment registers is not handled $end
$upscope $end
$upscope $end
$enddefinitions $end
#0
0!
1"
b00000000000000000000000000000000 #
bUUUUUUUUUUUUUUUUUUUUUUUUUUUUUUUU $
bUUUUUUUUUUUUUUUUUUUUUUUUUUUUUUUU %
bUUUUU &
bUUUUU '
b00000 (
0)
b00000000000000000000000000000000 *
bUUUUUUUUUUUUUUUUUUUUUUUUUUUUUUUU +
bUUUUUUUUUUUUUUUUUUUUUUUUUUUUUUUU ,
bUUUUU -
bUUUUU .
b00000 /
10
#10000000
1!
b00000000000000000000000000000000 $
b00000000000000000000000000000000 %
1)
b00000000000000000000000000000000 +
b00000000000000000000000000000000 ,
#20000000
0!
b00000000000000000000000000000001 #
b00001 (
0)
b00000000000000000000000000000001 *
b00001 /
#30000000
1!
1)
#40000000
0!
b00000000000000000000000000000010 #
b00010 (
0)
b00000000000000000000000000000010 *
b00010 /
#50000000
1!
1)
#60000000
0!
b00000000000000000000000000000011 #
b00011 (
0)
b00000000000000000000000000000011 *
b00011 /
#70000000
1!
1)
#80000000
0!
b00000000000000000000000000000100 #
b00100 (
0)
b00000000000000000000000000000100 *
b00100 /
#90000000
1!
1)
#100000000
0!
b00000000000000000000000000000101 #
b00101 (
0)
b00000000000000000000000000000101 *
b00101 /
#110000000
1!
1)
#120000000
0!
b00000000000000000000000000000110 #
b00110 (
0)
b00000000000000000000000000000110 *
b00110 /
#130000000
1!
1)
#140000000
0!
b00000000000000000000000000000111 #
b00111 (
0)
b00000000000000000000000000000111 *
b00111 /
#150000000
1!
1)
#160000000
0!
b00000000000000000000000000001000 #
b01000 (
0)
b00000000000000000000000000001000 *
b01000 /
#170000000
1!
1)
#180000000
0!
b00000000000000000000000000001001 #
b01001 (
0)
b00000000000000000000000000001001 *
b01001 /
#190000000
1!
1)
#200000000
0!
b00000000000000000000000000001010 #
b01010 (
0)
b00000000000000000000000000001010 *
b01010 /
#210000000
1!
1)
#220000000
0!
b00000000000000000000000000001011 #
b01011 (
0)
b00000000000000000000000000001011 *
b01011 /
#230000000
1!
1)
#240000000
0!
b00000000000000000000000000001100 #
b01100 (
0)
b00000000000000000000000000001100 *
b01100 /
#250000000
1!
1)
#260000000
0!
b00000000000000000000000000001101 #
b01101 (
0)
b00000000000000000000000000001101 *
b01101 /
#270000000
1!
1)
#280000000
0!
b00000000000000000000000000001110 #
b01110 (
0)
b00000000000000000000000000001110 *
b01110 /
#290000000
1!
1)
#300000000
0!
b00000000000000000000000000001111 #
b01111 (
0)
b00000000000000000000000000001111 *
b01111 /
#310000000
1!
1)
#320000000
0!
b00000000000000000000000000010000 #
b10000 (
0)
b00000000000000000000000000010000 *
b10000 /
#330000000
1!
1)
#340000000
0!
b00000000000000000000000000010001 #
b10001 (
0)
b00000000000000000000000000010001 *
b10001 /
#350000000
1!
1)
#360000000
0!
b00000000000000000000000000010010 #
b10010 (
0)
b00000000000000000000000000010010 *
b10010 /
#370000000
1!
1)
#380000000
0!
b00000000000000000000000000010011 #
b10011 (
0)
b00000000000000000000000000010011 *
b10011 /
#390000000
1!
1)
#400000000
0!
b00000000000000000000000000010100 #
b10100 (
0)
b00000000000000000000000000010100 *
b10100 /
#410000000
1!
1)
#420000000
0!
b00000000000000000000000000010101 #
b10101 (
0)
b00000000000000000000000000010101 *
b10101 /
#430000000
1!
1)
#440000000
0!
b00000000000000000000000000010110 #
b10110 (
0)
b00000000000000000000000000010110 *
b10110 /
#450000000
1!
1)
#460000000
0!
b00000000000000000000000000010111 #
b10111 (
0)
b00000000000000000000000000010111 *
b10111 /
#470000000
1!
1)
#480000000
0!
b00000000000000000000000000011000 #
b11000 (
0)
b00000000000000000000000000011000 *
b11000 /
#490000000
1!
1)
#500000000
0!
b00000000000000000000000000011001 #
b11001 (
0)
b00000000000000000000000000011001 *
b11001 /
#510000000
1!
1)
#520000000
0!
b00000000000000000000000000011010 #
b11010 (
0)
b00000000000000000000000000011010 *
b11010 /
#530000000
1!
1)
#540000000
0!
b00000000000000000000000000011011 #
b11011 (
0)
b00000000000000000000000000011011 *
b11011 /
#550000000
1!
1)
#560000000
0!
b00000000000000000000000000011100 #
b11100 (
0)
b00000000000000000000000000011100 *
b11100 /
#570000000
1!
1)
#580000000
0!
b00000000000000000000000000011101 #
b11101 (
0)
b00000000000000000000000000011101 *
b11101 /
#590000000
1!
1)
#600000000
0!
b00000000000000000000000000011110 #
b11110 (
0)
b00000000000000000000000000011110 *
b11110 /
#610000000
1!
1)
#620000000
0!
b00000000000000000000000000011111 #
b11111 (
0)
b00000000000000000000000000011111 *
b11111 /
#630000000
1!
1)
#640000000
0!
b10101010101010101010101010101010 #
b00000000000000000000000000001010 %
b00000 &
b01010 '
b00000 (
0)
b10101010101010101010101010101010 *
b00000000000000000000000000001010 ,
b00000 -
b01010 .
b00000 /
#650000000
1!
b10101010101010101010101010101010 $
1)
b10101010101010101010101010101010 +
#660000000
0!
b01010101010101010101010101010101 #
b01010 (
0)
b01010101010101010101010101010101 *
b01010 /
#670000000
1!
b01010101010101010101010101010101 %
1)
b01010101010101010101010101010101 ,
